youtube_rss_subscriber/__init__.py
youtube_rss_subscriber/config.py
youtube_rss_subscriber/download.py
youtube_rss_subscriber/schema.py
youtube_rss_subscriber-0.0.6.dist-info/LICENSE
youtube_rss_subscriber-0.0.6.dist-info/METADATA
youtube_rss_subscriber-0.0.6.dist-info/WHEEL
youtube_rss_subscriber-0.0.6.dist-info/entry_points.txt
youtube_rss_subscriber-0.0.6.dist-info/top_level.txt
youtube_rss_subscriber-0.0.6.dist-info/RECORD
